{
  "updated": "16/07/2026 02:43 UTC",
  "sports": {
    "bk": [
      {
        "vid": "Jj3Iok1tO5s",
        "title": "CELTICS vs KINGS | LAS VEGAS SUMMER LEAGUE | FULL GAME HIGHLIGHTS | July 15, 2026",
        "thumb": "https://i.ytimg.com/vi/Jj3Iok1tO5s/mqdefault.jpg",
        "date": "2026-07-16",
        "url": "https://www.youtube.com/watch?v=Jj3Iok1tO5s"
      },
      {
        "vid": "OXk7iSE_q5E",
        "title": "Darryn Peterson gets the chase down block &amp; turns defense to offense 😤",
        "thumb": "https://i.ytimg.com/vi/OXk7iSE_q5E/mqdefault.jpg",
        "date": "2026-07-16",
        "url": "https://www.youtube.com/watch?v=OXk7iSE_q5E"
      },
      {
        "vid": "ayVu_t_PVTk",
        "title": "Milicic Jr. goes all the way into the stands to save it!",
        "thumb": "https://i.ytimg.com/vi/ayVu_t_PVTk/mqdefault.jpg",
        "date": "2026-07-16",
        "url": "https://www.youtube.com/watch?v=ayVu_t_PVTk"
      },
      {
        "vid": "Pj8Tp_XglfM",
        "title": "BUCKS vs HORNETS | LAS VEGAS SUMMER LEAGUE | FULL GAME HIGHLIGHTS | July 15, 2026",
        "thumb": "https://i.ytimg.com/vi/Pj8Tp_XglfM/mqdefault.jpg",
        "date": "2026-07-16",
        "url": "https://www.youtube.com/watch?v=Pj8Tp_XglfM"
      },
      {
        "vid": "eK6jiTv24ao",
        "title": "Nate Ament No. 13 Overall Pick SHINED with 23 PTS | July 15, 2026",
        "thumb": "https://i.ytimg.com/vi/eK6jiTv24ao/mqdefault.jpg",
        "date": "2026-07-16",
        "url": "https://www.youtube.com/watch?v=eK6jiTv24ao"
      },
      {
        "vid": "si0VTaX8Q5s",
        "title": "AJ Dybantsa Summer League Debut Full Play | 27 Pts, 7 Rebs 🔥🔥",
        "thumb": "https://i.ytimg.com/vi/si0VTaX8Q5s/mqdefault.jpg",
        "date": "2026-07-10",
        "url": "https://www.youtube.com/watch?v=si0VTaX8Q5s"
      },
      {
        "vid": "d51kqvLmjGQ",
        "title": "San Antonio Spurs vs Minnesota Timberwolves Game 2 Full Highlights | 2026 WCSF | FreeDawkins",
        "thumb": "https://i.ytimg.com/vi/d51kqvLmjGQ/mqdefault.jpg",
        "date": "2026-05-07",
        "url": "https://www.youtube.com/watch?v=d51kqvLmjGQ"
      },
      {
        "vid": "TRnc5Ef8uGY",
        "title": "San Antonio Spurs vs Portland Trailblazers Game 5 Full Highlights | 2026 WCR1 | FreeDawkins",
        "thumb": "https://i.ytimg.com/vi/TRnc5Ef8uGY/mqdefault.jpg",
        "date": "2026-04-29",
        "url": "https://www.youtube.com/watch?v=TRnc5Ef8uGY"
      }
    ],
    "pd": [
      {
        "vid": "XdpDwMnHLTI",
        "title": "Malaga Premier Padel P1 🇪🇸🎾: Day 3 - Men&#39;s Highlights",
        "thumb": "https://i.ytimg.com/vi/XdpDwMnHLTI/mqdefault.jpg",
        "date": "2026-07-15",
        "url": "https://www.youtube.com/watch?v=XdpDwMnHLTI"
      },
      {
        "vid": "tn81D3MvKUU",
        "title": "Malaga Premier Padel P1 🇪🇸🎾: Day 3 - Women&#39;s Highlights",
        "thumb": "https://i.ytimg.com/vi/tn81D3MvKUU/mqdefault.jpg",
        "date": "2026-07-15",
        "url": "https://www.youtube.com/watch?v=tn81D3MvKUU"
      },
      {
        "vid": "4zjRAbYjXwg",
        "title": "Malaga Premier Padel P1 🇪🇸🎾: Centre Court (🇬🇧)",
        "thumb": "https://i.ytimg.com/vi/4zjRAbYjXwg/mqdefault_live.jpg",
        "date": "2026-07-15",
        "url": "https://www.youtube.com/watch?v=4zjRAbYjXwg"
      },
      {
        "vid": "VzPET1vFQZ4",
        "title": "Malaga Premier Padel P1 🇪🇸🎾: Pista Central (🇪🇸)",
        "thumb": "https://i.ytimg.com/vi/VzPET1vFQZ4/mqdefault_live.jpg",
        "date": "2026-07-15",
        "url": "https://www.youtube.com/watch?v=VzPET1vFQZ4"
      },
      {
        "vid": "lDVLr9byKWE",
        "title": "Malaga Premier Padel P1 🇪🇸🎾: Court 2",
        "thumb": "https://i.ytimg.com/vi/lDVLr9byKWE/mqdefault_live.jpg",
        "date": "2026-07-15",
        "url": "https://www.youtube.com/watch?v=lDVLr9byKWE"
      }
    ],
    "fx": [
      {
        "vid": "uvId2AgzwTA",
        "title": "Messi ✨",
        "thumb": "https://i.ytimg.com/vi/uvId2AgzwTA/mqdefault.jpg",
        "date": "2026-07-16",
        "url": "https://www.youtube.com/watch?v=uvId2AgzwTA"
      },
      {
        "vid": "36UWARrdNpE",
        "title": "La increíble evolución de CUBARSÍ 🇪🇸⭐️",
        "thumb": "https://i.ytimg.com/vi/36UWARrdNpE/mqdefault.jpg",
        "date": "2026-07-15",
        "url": "https://www.youtube.com/watch?v=36UWARrdNpE"
      },
      {
        "vid": "GgmmywQmxPU",
        "title": "Las 10 MEJORES puntuaciones de LAMINE YAMAL en LALIGA FANTASY ⭐",
        "thumb": "https://i.ytimg.com/vi/GgmmywQmxPU/mqdefault.jpg",
        "date": "2026-07-15",
        "url": "https://www.youtube.com/watch?v=GgmmywQmxPU"
      },
      {
        "vid": "TgkwQj6iGY0",
        "title": "La calidad de JULIÁN ALVAREZ",
        "thumb": "https://i.ytimg.com/vi/TgkwQj6iGY0/mqdefault.jpg",
        "date": "2026-07-15",
        "url": "https://www.youtube.com/watch?v=TgkwQj6iGY0"
      },
      {
        "vid": "Pi5FjaCLTbE",
        "title": "ARGENTINA vs INGLATERRA: LOS MEJORES GOLES de LALIGA 🇦🇷🔥🏴",
        "thumb": "https://i.ytimg.com/vi/Pi5FjaCLTbE/mqdefault.jpg",
        "date": "2026-07-15",
        "url": "https://www.youtube.com/watch?v=Pi5FjaCLTbE"
      },
      {
        "vid": "6DrZdpFpg2c",
        "title": "Dizzying Messi 😵‍💫",
        "thumb": "https://i.ytimg.com/vi/6DrZdpFpg2c/mqdefault.jpg",
        "date": "2026-07-15",
        "url": "https://www.youtube.com/watch?v=6DrZdpFpg2c"
      },
      {
        "vid": "HLmwwRGM-K4",
        "title": "EVERY Antoine Griezmann Champions League Goal",
        "thumb": "https://i.ytimg.com/vi/HLmwwRGM-K4/mqdefault.jpg",
        "date": "2026-07-14",
        "url": "https://www.youtube.com/watch?v=HLmwwRGM-K4"
      },
      {
        "vid": "8zDWF-DQGvI",
        "title": "Doué’s assist for Barcola 🤝",
        "thumb": "https://i.ytimg.com/vi/8zDWF-DQGvI/mqdefault.jpg",
        "date": "2026-07-14",
        "url": "https://www.youtube.com/watch?v=8zDWF-DQGvI"
      }
    ]
  }
}