{
  "updated": "02/05/2026 02:52 UTC",
  "sports": {
    "bk": [
      {
        "vid": "-oP8Oq2ahmg",
        "title": "Detroit Pistons vs. Orlando Magic | Game 6 Postgame Media Availability",
        "thumb": "https://i.ytimg.com/vi/-oP8Oq2ahmg/mqdefault.jpg",
        "date": "2026-05-02",
        "url": "https://www.youtube.com/watch?v=-oP8Oq2ahmg"
      },
      {
        "vid": "sh2oGvgVRUA",
        "title": "RJ BARRETT IS UNBELIEVALE 😱😱😱",
        "thumb": "https://i.ytimg.com/vi/sh2oGvgVRUA/mqdefault.jpg",
        "date": "2026-05-02",
        "url": "https://www.youtube.com/watch?v=sh2oGvgVRUA"
      },
      {
        "vid": "Kio8Z16wATU",
        "title": "Pistons Complete HISTORIC 24-PT Comeback in Elimination Game 6 🤯 | May 1, 2026",
        "thumb": "https://i.ytimg.com/vi/Kio8Z16wATU/mqdefault.jpg",
        "date": "2026-05-02",
        "url": "https://www.youtube.com/watch?v=Kio8Z16wATU"
      },
      {
        "vid": "l3WDCimY3MI",
        "title": "Pistons put up the largest road comeback in a postseason elimination game in the play-by-play era 🚨",
        "thumb": "https://i.ytimg.com/vi/l3WDCimY3MI/mqdefault.jpg",
        "date": "2026-05-02",
        "url": "https://www.youtube.com/watch?v=l3WDCimY3MI"
      },
      {
        "vid": "c0KF-7TO9RE",
        "title": "LeBron baseball assist 🤯 ⚾️",
        "thumb": "https://i.ytimg.com/vi/c0KF-7TO9RE/mqdefault.jpg",
        "date": "2026-05-02",
        "url": "https://www.youtube.com/watch?v=c0KF-7TO9RE"
      },
      {
        "vid": "lhbeBbY4ruM",
        "title": "Denver Nuggets vs Minnesota Timberwolves Game 6 Full Highlights | 2026 WCR1 | FreeDawkins",
        "thumb": "https://i.ytimg.com/vi/lhbeBbY4ruM/mqdefault.jpg",
        "date": "2026-05-01",
        "url": "https://www.youtube.com/watch?v=lhbeBbY4ruM"
      },
      {
        "vid": "zQmkFqzNZJ0",
        "title": "Los Angeles Lakers vs Houston Rockets Game 5 Full Highlights | 2026 WCR1 | FreeDawkins",
        "thumb": "https://i.ytimg.com/vi/zQmkFqzNZJ0/mqdefault.jpg",
        "date": "2026-04-30",
        "url": "https://www.youtube.com/watch?v=zQmkFqzNZJ0"
      },
      {
        "vid": "TRnc5Ef8uGY",
        "title": "San Antonio Spurs vs Portland Trailblazers Game 5 Full Highlights | 2026 WCR1 | FreeDawkins",
        "thumb": "https://i.ytimg.com/vi/TRnc5Ef8uGY/mqdefault.jpg",
        "date": "2026-04-29",
        "url": "https://www.youtube.com/watch?v=TRnc5Ef8uGY"
      }
    ],
    "pd": [
      {
        "vid": "LIoyR8gmQj4",
        "title": "Sanz returns the ball behind his back in the Brussels P2",
        "thumb": "https://i.ytimg.com/vi/LIoyR8gmQj4/mqdefault.jpg",
        "date": "2026-04-22",
        "url": "https://www.youtube.com/watch?v=LIoyR8gmQj4"
      },
      {
        "vid": "ZPxKVTEADfk",
        "title": "Great winner shot by Galan in the NEWGIZA P2",
        "thumb": "https://i.ytimg.com/vi/ZPxKVTEADfk/mqdefault.jpg",
        "date": "2026-04-18",
        "url": "https://www.youtube.com/watch?v=ZPxKVTEADfk"
      },
      {
        "vid": "b7Tei9qRdqk",
        "title": "NewGiza Premier Padel P2 🇪🇬🎾: Day 2 - Men&#39;s Highlights",
        "thumb": "https://i.ytimg.com/vi/b7Tei9qRdqk/mqdefault.jpg",
        "date": "2026-04-15",
        "url": "https://www.youtube.com/watch?v=b7Tei9qRdqk"
      },
      {
        "vid": "XSd-r-ZYuag",
        "title": "Insane volley winner by Josemaria in the Miami Premier Padel P1",
        "thumb": "https://i.ytimg.com/vi/XSd-r-ZYuag/mqdefault.jpg",
        "date": "2026-03-29",
        "url": "https://www.youtube.com/watch?v=XSd-r-ZYuag"
      },
      {
        "vid": "uweOyzVoZEs",
        "title": "What a great point from Paquito Navarro 😮‍💨🎸#PremierPadel #MiamiPremierPadelP1",
        "thumb": "https://i.ytimg.com/vi/uweOyzVoZEs/mqdefault.jpg",
        "date": "2026-03-28",
        "url": "https://www.youtube.com/watch?v=uweOyzVoZEs"
      }
    ],
    "fx": [
      {
        "vid": "ZfpnllFkp_g",
        "title": "GIRONA FC vs RCD MALLORCA | RUEDA DE PRENSA",
        "thumb": "https://i.ytimg.com/vi/ZfpnllFkp_g/mqdefault.jpg",
        "date": "2026-05-01",
        "url": "https://www.youtube.com/watch?v=ZfpnllFkp_g"
      },
      {
        "vid": "niVzhHzzeqQ",
        "title": "GIRONA FC 0 - 1 RCD MALLORCA | RESUMEN LALIGA EA SPORTS",
        "thumb": "https://i.ytimg.com/vi/niVzhHzzeqQ/mqdefault.jpg",
        "date": "2026-05-01",
        "url": "https://www.youtube.com/watch?v=niVzhHzzeqQ"
      },
      {
        "vid": "RoW0YEVk5GI",
        "title": "🤯🤯🤯🤯🤯🤯🤯🤯🤯",
        "thumb": "https://i.ytimg.com/vi/RoW0YEVk5GI/mqdefault.jpg",
        "date": "2026-05-01",
        "url": "https://www.youtube.com/watch?v=RoW0YEVk5GI"
      },
      {
        "vid": "1vkpPEi4zsk",
        "title": "SAMÚ COSTA❤️⚽️",
        "thumb": "https://i.ytimg.com/vi/1vkpPEi4zsk/mqdefault.jpg",
        "date": "2026-05-01",
        "url": "https://www.youtube.com/watch?v=1vkpPEi4zsk"
      },
      {
        "vid": "M_d_1lwhyJM",
        "title": "El arte de defender. ⚔️",
        "thumb": "https://i.ytimg.com/vi/M_d_1lwhyJM/mqdefault.jpg",
        "date": "2026-05-01",
        "url": "https://www.youtube.com/watch?v=M_d_1lwhyJM"
      },
      {
        "vid": "qk5IIYbOljE",
        "title": "Jørgen Strand Larsen 🤯",
        "thumb": "https://i.ytimg.com/vi/qk5IIYbOljE/mqdefault.jpg",
        "date": "2026-05-01",
        "url": "https://www.youtube.com/watch?v=qk5IIYbOljE"
      },
      {
        "vid": "h86mkInnH5Y",
        "title": "The fastest goal in Conference League history!!! 🤯",
        "thumb": "https://i.ytimg.com/vi/h86mkInnH5Y/mqdefault.jpg",
        "date": "2026-05-01",
        "url": "https://www.youtube.com/watch?v=h86mkInnH5Y"
      },
      {
        "vid": "OJKUUtnVGHI",
        "title": "Madrid or Braga? 🗺️",
        "thumb": "https://i.ytimg.com/vi/OJKUUtnVGHI/mqdefault.jpg",
        "date": "2026-05-01",
        "url": "https://www.youtube.com/watch?v=OJKUUtnVGHI"
      }
    ]
  }
}