{
  "updated": "10/07/2026 10:56 UTC",
  "sports": {
    "bk": [
      {
        "vid": "c33ZiMR9usk",
        "title": "NBA&#39;s Nightly Recap | July 9, 2026",
        "thumb": "https://i.ytimg.com/vi/c33ZiMR9usk/mqdefault.jpg",
        "date": "2026-07-10",
        "url": "https://www.youtube.com/watch?v=c33ZiMR9usk"
      },
      {
        "vid": "L2fSD4UD-Yg",
        "title": "PlayStation NBA CREATOR CUP | FULL GAME HIGHLIGHTS | July 9, 2026",
        "thumb": "https://i.ytimg.com/vi/L2fSD4UD-Yg/mqdefault.jpg",
        "date": "2026-07-10",
        "url": "https://www.youtube.com/watch?v=L2fSD4UD-Yg"
      },
      {
        "vid": "V9aZBhlQwAI",
        "title": "KINGS vs CLIPPERS | LAS VEGAS SUMMER LEAGUE | FULL GAME HIGHLIGHTS | July 9, 2026",
        "thumb": "https://i.ytimg.com/vi/V9aZBhlQwAI/mqdefault.jpg",
        "date": "2026-07-10",
        "url": "https://www.youtube.com/watch?v=V9aZBhlQwAI"
      },
      {
        "vid": "vzmsTZO84L4",
        "title": "LeeThe4th is the NBA Creator Cup MVP!",
        "thumb": "https://i.ytimg.com/vi/vzmsTZO84L4/mqdefault.jpg",
        "date": "2026-07-10",
        "url": "https://www.youtube.com/watch?v=vzmsTZO84L4"
      },
      {
        "vid": "al8TZ2_n5Xs",
        "title": "PlayStation NBA Creator Cup [Official Stream]",
        "thumb": "https://i.ytimg.com/vi/al8TZ2_n5Xs/mqdefault.jpg",
        "date": "2026-07-10",
        "url": "https://www.youtube.com/watch?v=al8TZ2_n5Xs"
      },
      {
        "vid": "si0VTaX8Q5s",
        "title": "AJ Dybantsa Summer League Debut Full Play | 27 Pts, 7 Rebs 🔥🔥",
        "thumb": "https://i.ytimg.com/vi/si0VTaX8Q5s/mqdefault.jpg",
        "date": "2026-07-10",
        "url": "https://www.youtube.com/watch?v=si0VTaX8Q5s"
      },
      {
        "vid": "d51kqvLmjGQ",
        "title": "San Antonio Spurs vs Minnesota Timberwolves Game 2 Full Highlights | 2026 WCSF | FreeDawkins",
        "thumb": "https://i.ytimg.com/vi/d51kqvLmjGQ/mqdefault.jpg",
        "date": "2026-05-07",
        "url": "https://www.youtube.com/watch?v=d51kqvLmjGQ"
      },
      {
        "vid": "TRnc5Ef8uGY",
        "title": "San Antonio Spurs vs Portland Trailblazers Game 5 Full Highlights | 2026 WCR1 | FreeDawkins",
        "thumb": "https://i.ytimg.com/vi/TRnc5Ef8uGY/mqdefault.jpg",
        "date": "2026-04-29",
        "url": "https://www.youtube.com/watch?v=TRnc5Ef8uGY"
      }
    ],
    "pd": [
      {
        "vid": "OCRn0_3LqFc",
        "title": "El fin de una era: Lamperti, Salazar y el legado del pádel | Bandeja Ep 3",
        "thumb": "https://i.ytimg.com/vi/OCRn0_3LqFc/mqdefault.jpg",
        "date": "2026-07-09",
        "url": "https://www.youtube.com/watch?v=OCRn0_3LqFc"
      },
      {
        "vid": "1iX-eCvsEX0",
        "title": "Is playing only on the right or left over in padel? 🤔",
        "thumb": "https://i.ytimg.com/vi/1iX-eCvsEX0/mqdefault.jpg",
        "date": "2026-07-09",
        "url": "https://www.youtube.com/watch?v=1iX-eCvsEX0"
      },
      {
        "vid": "v1Cn_GnWk6g",
        "title": "Official Presentation | Andaluciá Málaga Premier Padel P1 🇪🇸",
        "thumb": "https://i.ytimg.com/vi/v1Cn_GnWk6g/mqdefault.jpg",
        "date": "2026-07-09",
        "url": "https://www.youtube.com/watch?v=v1Cn_GnWk6g"
      },
      {
        "vid": "WLiFY1WmXJc",
        "title": "A year ago Sofi Araujo did this amazing return and smashed it for the point 😮‍💨🦁 #PremierPadel",
        "thumb": "https://i.ytimg.com/vi/WLiFY1WmXJc/mqdefault.jpg",
        "date": "2026-07-08",
        "url": "https://www.youtube.com/watch?v=WLiFY1WmXJc"
      },
      {
        "vid": "KdvJznpmJZ8",
        "title": "La Mentalidad de ganador: Tapia sobre Coello, Messi y el entrenamiento invisible | Bandeja Ep 2",
        "thumb": "https://i.ytimg.com/vi/KdvJznpmJZ8/mqdefault.jpg",
        "date": "2026-07-02",
        "url": "https://www.youtube.com/watch?v=KdvJznpmJZ8"
      }
    ],
    "fx": [
      {
        "vid": "7fV7XuiaUpU",
        "title": "¿Conoces un “parapenaltis” mejor que Bono?",
        "thumb": "https://i.ytimg.com/vi/7fV7XuiaUpU/mqdefault.jpg",
        "date": "2026-07-10",
        "url": "https://www.youtube.com/watch?v=7fV7XuiaUpU"
      },
      {
        "vid": "OXbGmuA1JgE",
        "title": "Modo drama del Barça ✨",
        "thumb": "https://i.ytimg.com/vi/OXbGmuA1JgE/mqdefault.jpg",
        "date": "2026-07-10",
        "url": "https://www.youtube.com/watch?v=OXbGmuA1JgE"
      },
      {
        "vid": "VTGkHne1Oac",
        "title": "La asistencia de Ferran Torres 🫣",
        "thumb": "https://i.ytimg.com/vi/VTGkHne1Oac/mqdefault.jpg",
        "date": "2026-07-09",
        "url": "https://www.youtube.com/watch?v=VTGkHne1Oac"
      },
      {
        "vid": "55jvnJZCTjM",
        "title": "Valencia CF 3 - 1 FC Barcelona 2025/26 PARTIDO COMPLETO",
        "thumb": "https://i.ytimg.com/vi/55jvnJZCTjM/mqdefault.jpg",
        "date": "2026-07-09",
        "url": "https://www.youtube.com/watch?v=55jvnJZCTjM"
      },
      {
        "vid": "UFMNLsrvQTk",
        "title": "Mbappé vs Brahim 🇫🇷🆚🇲🇦",
        "thumb": "https://i.ytimg.com/vi/UFMNLsrvQTk/mqdefault.jpg",
        "date": "2026-07-09",
        "url": "https://www.youtube.com/watch?v=UFMNLsrvQTk"
      },
      {
        "vid": "p7TupOv4t08",
        "title": "Osimhen ⚡️⚡️⚡️",
        "thumb": "https://i.ytimg.com/vi/p7TupOv4t08/mqdefault.jpg",
        "date": "2026-07-09",
        "url": "https://www.youtube.com/watch?v=p7TupOv4t08"
      },
      {
        "vid": "jkz6OZMgTQs",
        "title": "INCREDIBLE Goals Scored By The World Cup Quarter-Finalists!",
        "thumb": "https://i.ytimg.com/vi/jkz6OZMgTQs/mqdefault.jpg",
        "date": "2026-07-08",
        "url": "https://www.youtube.com/watch?v=jkz6OZMgTQs"
      },
      {
        "vid": "p4xy6UWrACI",
        "title": "Can’t stop, won’t stop",
        "thumb": "https://i.ytimg.com/vi/p4xy6UWrACI/mqdefault.jpg",
        "date": "2026-07-08",
        "url": "https://www.youtube.com/watch?v=p4xy6UWrACI"
      }
    ]
  }
}