{
  "updated": "26/03/2026 19:40 UTC",
  "sports": {
    "bk": [
      {
        "vid": "5zIj7vA0sMs",
        "title": "Jamal Murray’s 50-Point Performances… All 4 of Them 😳",
        "thumb": "https://i.ytimg.com/vi/5zIj7vA0sMs/mqdefault.jpg",
        "date": "2026-03-26",
        "url": "https://www.youtube.com/watch?v=5zIj7vA0sMs"
      },
      {
        "vid": "T-DG1QtT0HI",
        "title": "The CRAZIEST 12-Game NBA Night of the Season 😱 | March 25, 2026",
        "thumb": "https://i.ytimg.com/vi/T-DG1QtT0HI/mqdefault.jpg",
        "date": "2026-03-26",
        "url": "https://www.youtube.com/watch?v=T-DG1QtT0HI"
      },
      {
        "vid": "-3A9xK-QY5E",
        "title": "NBA&#39;s Nightly Recap | March 25, 2026",
        "thumb": "https://i.ytimg.com/vi/-3A9xK-QY5E/mqdefault.jpg",
        "date": "2026-03-26",
        "url": "https://www.youtube.com/watch?v=-3A9xK-QY5E"
      },
      {
        "vid": "Fax2kk6IXPQ",
        "title": "EXTENDED: ROCKETS at TIMBERWOLVES | FULL GAME HIGHLIGHTS | March 25, 2026",
        "thumb": "https://i.ytimg.com/vi/Fax2kk6IXPQ/mqdefault.jpg",
        "date": "2026-03-26",
        "url": "https://www.youtube.com/watch?v=Fax2kk6IXPQ"
      },
      {
        "vid": "m9_QFs-VmO4",
        "title": "Lakers Hype Moments 25/26 Season UNCUT 🔥 | LBJ&#39;s Dunk at WAS #shorts #nba #basketball",
        "thumb": "https://i.ytimg.com/vi/m9_QFs-VmO4/mqdefault.jpg",
        "date": "2026-03-26",
        "url": "https://www.youtube.com/watch?v=m9_QFs-VmO4"
      },
      {
        "vid": "rRsQQnEXi9c",
        "title": "Lakers Hype Moments 25/26 Season UNCUT 🔥 | LBJ&#39;s Takeover at PHI #shorts #nba #basketball",
        "thumb": "https://i.ytimg.com/vi/rRsQQnEXi9c/mqdefault.jpg",
        "date": "2026-03-26",
        "url": "https://www.youtube.com/watch?v=rRsQQnEXi9c"
      },
      {
        "vid": "KS1KlPaOMsU",
        "title": "Spurs Hype Moments 25/26 Season UNCUT 🔥 | Castle&#39;s Facial at MEM #shorts #nba #basketball #sports",
        "thumb": "https://i.ytimg.com/vi/KS1KlPaOMsU/mqdefault.jpg",
        "date": "2026-03-26",
        "url": "https://www.youtube.com/watch?v=KS1KlPaOMsU"
      },
      {
        "vid": "TeXch4MTM-w",
        "title": "Spurs Hype Moments 25/26 Season UNCUT 🔥 | Wemby&#39;s Facial at MEM #shorts #nba #basketball #sports",
        "thumb": "https://i.ytimg.com/vi/TeXch4MTM-w/mqdefault.jpg",
        "date": "2026-03-26",
        "url": "https://www.youtube.com/watch?v=TeXch4MTM-w"
      }
    ],
    "pd": [
      {
        "vid": "U7Umq5fSoBA",
        "title": "Such a spot on x3 point from Vero Virseda 🔥 #PremierPadel #MiamiPremierPadelP1",
        "thumb": "https://i.ytimg.com/vi/U7Umq5fSoBA/mqdefault.jpg",
        "date": "2026-03-26",
        "url": "https://www.youtube.com/watch?v=U7Umq5fSoBA"
      },
      {
        "vid": "LfkhMyjwjLo",
        "title": "Miami Premier Padel P1 🇺🇸🎾: Court 2",
        "thumb": "https://i.ytimg.com/vi/LfkhMyjwjLo/mqdefault.jpg",
        "date": "2026-03-26",
        "url": "https://www.youtube.com/watch?v=LfkhMyjwjLo"
      },
      {
        "vid": "57EH6-5zsBg",
        "title": "Miami Premier Padel P1🇺🇸🎾: Day 3 - Women Highlight",
        "thumb": "https://i.ytimg.com/vi/57EH6-5zsBg/mqdefault.jpg",
        "date": "2026-03-26",
        "url": "https://www.youtube.com/watch?v=57EH6-5zsBg"
      },
      {
        "vid": "KoHKPfMsEG8",
        "title": "Miami Premier Padel P1🇺🇸🎾: Day 3 - Men Highlight",
        "thumb": "https://i.ytimg.com/vi/KoHKPfMsEG8/mqdefault.jpg",
        "date": "2026-03-26",
        "url": "https://www.youtube.com/watch?v=KoHKPfMsEG8"
      },
      {
        "vid": "RStx1OtPNK0",
        "title": "(Replay) Miami Premier Padel P1🇺🇸🎾: Court 2 (March 25th)",
        "thumb": "https://i.ytimg.com/vi/RStx1OtPNK0/mqdefault.jpg",
        "date": "2026-03-26",
        "url": "https://www.youtube.com/watch?v=RStx1OtPNK0"
      }
    ],
    "fx": [
      {
        "vid": "lJ-38uTO2hE",
        "title": "Fase de grupos de LALIGA FC FUTURES",
        "thumb": "https://i.ytimg.com/vi/lJ-38uTO2hE/mqdefault.jpg",
        "date": "2026-03-26",
        "url": "https://www.youtube.com/watch?v=lJ-38uTO2hE"
      },
      {
        "vid": "AlpJv30RbSY",
        "title": "Los tres futbolistas con más conducciones de alto impacto son…",
        "thumb": "https://i.ytimg.com/vi/AlpJv30RbSY/mqdefault.jpg",
        "date": "2026-03-26",
        "url": "https://www.youtube.com/watch?v=AlpJv30RbSY"
      },
      {
        "vid": "P68E9RMVUjw",
        "title": "Las 50 MEJORES GOLES hasta la fecha en LALIGA 2025/26 🔥",
        "thumb": "https://i.ytimg.com/vi/P68E9RMVUjw/mqdefault.jpg",
        "date": "2026-03-26",
        "url": "https://www.youtube.com/watch?v=P68E9RMVUjw"
      },
      {
        "vid": "mgqAy0S7HQs",
        "title": "Apunten este nombre: HUGO GALDEANO ✨",
        "thumb": "https://i.ytimg.com/vi/mgqAy0S7HQs/mqdefault.jpg",
        "date": "2026-03-26",
        "url": "https://www.youtube.com/watch?v=mgqAy0S7HQs"
      },
      {
        "vid": "e57UALUCDB4",
        "title": "Fase de grupos de LALIGA FC FUTURES",
        "thumb": "https://i.ytimg.com/vi/e57UALUCDB4/mqdefault.jpg",
        "date": "2026-03-26",
        "url": "https://www.youtube.com/watch?v=e57UALUCDB4"
      },
      {
        "vid": "AwGo4TFROtY",
        "title": "The Killers x UCL Final Kick Off Show by Pepsi | 30th May",
        "thumb": "https://i.ytimg.com/vi/AwGo4TFROtY/mqdefault.jpg",
        "date": "2026-03-26",
        "url": "https://www.youtube.com/watch?v=AwGo4TFROtY"
      },
      {
        "vid": "i5enxNflucQ",
        "title": "How good was Ronaldinho?",
        "thumb": "https://i.ytimg.com/vi/i5enxNflucQ/mqdefault.jpg",
        "date": "2026-03-25",
        "url": "https://www.youtube.com/watch?v=i5enxNflucQ"
      },
      {
        "vid": "vJg2wa1-TF8",
        "title": "Why Ronaldinho Is One Of The Greatest Of All Time! 🇧🇷",
        "thumb": "https://i.ytimg.com/vi/vJg2wa1-TF8/mqdefault.jpg",
        "date": "2026-03-25",
        "url": "https://www.youtube.com/watch?v=vJg2wa1-TF8"
      }
    ]
  }
}