{
  "updated": "15/06/2026 19:49 UTC",
  "sports": {
    "bk": [
      {
        "vid": "iZbBzQRSKxA",
        "title": "She was born a winner…literally 😂",
        "thumb": "https://i.ytimg.com/vi/iZbBzQRSKxA/mqdefault.jpg",
        "date": "2026-06-15",
        "url": "https://www.youtube.com/watch?v=iZbBzQRSKxA"
      },
      {
        "vid": "m6YdTaZeDnA",
        "title": "Jose Alvarado was hyping up Brunson at his presser 😂",
        "thumb": "https://i.ytimg.com/vi/m6YdTaZeDnA/mqdefault.jpg",
        "date": "2026-06-15",
        "url": "https://www.youtube.com/watch?v=m6YdTaZeDnA"
      },
      {
        "vid": "pgRPGyOwVG0",
        "title": "SCENES in NYC as the Knicks won their first championship in 53 years 🏆💙🧡(via: dini_inabottle/IG)",
        "thumb": "https://i.ytimg.com/vi/pgRPGyOwVG0/mqdefault.jpg",
        "date": "2026-06-15",
        "url": "https://www.youtube.com/watch?v=pgRPGyOwVG0"
      },
      {
        "vid": "biOEZ-xlaGg",
        "title": "Do your dance KAT 😂🍾",
        "thumb": "https://i.ytimg.com/vi/biOEZ-xlaGg/mqdefault.jpg",
        "date": "2026-06-15",
        "url": "https://www.youtube.com/watch?v=biOEZ-xlaGg"
      },
      {
        "vid": "-2gxGghUr_s",
        "title": "The Finals MVP Jalen Brunson popping champagne in the locker room 🍾",
        "thumb": "https://i.ytimg.com/vi/-2gxGghUr_s/mqdefault.jpg",
        "date": "2026-06-15",
        "url": "https://www.youtube.com/watch?v=-2gxGghUr_s"
      },
      {
        "vid": "GhvDbQoSo7s",
        "title": "San Antonio Spurs vs New York Knicks Game 5 Full Highlights | 2026 NBA Finals | FreeDawkins",
        "thumb": "https://i.ytimg.com/vi/GhvDbQoSo7s/mqdefault.jpg",
        "date": "2026-06-14",
        "url": "https://www.youtube.com/watch?v=GhvDbQoSo7s"
      },
      {
        "vid": "5isJaCP1J2s",
        "title": "PART2: San Antonio Spurs vs New York Knicks Game 4 Full Highlights | 2026 NBA Finals | FreeDawkins",
        "thumb": "https://i.ytimg.com/vi/5isJaCP1J2s/mqdefault.jpg",
        "date": "2026-06-11",
        "url": "https://www.youtube.com/watch?v=5isJaCP1J2s"
      },
      {
        "vid": "d51kqvLmjGQ",
        "title": "San Antonio Spurs vs Minnesota Timberwolves Game 2 Full Highlights | 2026 WCSF | FreeDawkins",
        "thumb": "https://i.ytimg.com/vi/d51kqvLmjGQ/mqdefault.jpg",
        "date": "2026-05-07",
        "url": "https://www.youtube.com/watch?v=d51kqvLmjGQ"
      }
    ],
    "pd": [
      {
        "vid": "7BBOpd210kU",
        "title": "Madrid Premier Padel P1: Official Presentation 🇪🇸",
        "thumb": "https://i.ytimg.com/vi/7BBOpd210kU/mqdefault.jpg",
        "date": "2026-06-15",
        "url": "https://www.youtube.com/watch?v=7BBOpd210kU"
      },
      {
        "vid": "GYdXsId0PEM",
        "title": "Valencia Premier Padel P1 🇪🇸🎾: Day 4 - Men&#39;s Highlights",
        "thumb": "https://i.ytimg.com/vi/GYdXsId0PEM/mqdefault.jpg",
        "date": "2026-06-11",
        "url": "https://www.youtube.com/watch?v=GYdXsId0PEM"
      },
      {
        "vid": "lT1ec_DME2c",
        "title": "Valencia Premier Padel P1 🇪🇸🎾: Day 4 - Women&#39;s Highlights",
        "thumb": "https://i.ytimg.com/vi/lT1ec_DME2c/mqdefault.jpg",
        "date": "2026-06-11",
        "url": "https://www.youtube.com/watch?v=lT1ec_DME2c"
      },
      {
        "vid": "pxhel4W-vBU",
        "title": "(Replay) Valencia Premier Padel P1 🇪🇸🎾: Centre Court (🇪🇸) (June 11th)",
        "thumb": "https://i.ytimg.com/vi/pxhel4W-vBU/mqdefault.jpg",
        "date": "2026-06-11",
        "url": "https://www.youtube.com/watch?v=pxhel4W-vBU"
      },
      {
        "vid": "sH-b2sC8Z74",
        "title": "(Replay) Valencia Premier Padel P1 🇪🇸🎾: Centre Court (🇬🇧) (June 11th - Part 2)",
        "thumb": "https://i.ytimg.com/vi/sH-b2sC8Z74/mqdefault.jpg",
        "date": "2026-06-11",
        "url": "https://www.youtube.com/watch?v=sH-b2sC8Z74"
      }
    ],
    "fx": [
      {
        "vid": "LGxFZfSsn34",
        "title": "¡Los 10 MEJORES GOLES del ATHLETIC CLUB en LALIGA 2025/26! ❤️🤍",
        "thumb": "https://i.ytimg.com/vi/LGxFZfSsn34/mqdefault.jpg",
        "date": "2026-06-15",
        "url": "https://www.youtube.com/watch?v=LGxFZfSsn34"
      },
      {
        "vid": "Ie6BgMpxyUU",
        "title": "Pura energía de MARC CUCURELLA 😮‍💨⚔️",
        "thumb": "https://i.ytimg.com/vi/Ie6BgMpxyUU/mqdefault.jpg",
        "date": "2026-06-15",
        "url": "https://www.youtube.com/watch?v=Ie6BgMpxyUU"
      },
      {
        "vid": "_E3Ui2axK6k",
        "title": "TODOS los GOLES y ASISTENCIAS de VINI JR en LALIGA 2025/26",
        "thumb": "https://i.ytimg.com/vi/_E3Ui2axK6k/mqdefault.jpg",
        "date": "2026-06-15",
        "url": "https://www.youtube.com/watch?v=_E3Ui2axK6k"
      },
      {
        "vid": "slmX_Q7J1FE",
        "title": "El asistente y el goleador. La magia del Málaga CF con Joaquín e Isco Alarcón. 💙",
        "thumb": "https://i.ytimg.com/vi/slmX_Q7J1FE/mqdefault.jpg",
        "date": "2026-06-15",
        "url": "https://www.youtube.com/watch?v=slmX_Q7J1FE"
      },
      {
        "vid": "u_PDVTCqbkw",
        "title": "Cosas de Rodri desde el principio 🔥⚽",
        "thumb": "https://i.ytimg.com/vi/u_PDVTCqbkw/mqdefault.jpg",
        "date": "2026-06-15",
        "url": "https://www.youtube.com/watch?v=u_PDVTCqbkw"
      },
      {
        "vid": "-dCmRP2KBBo",
        "title": "🇪🇸 EVERY Spain Goal To Qualify For The World Cup 2026 | Highights",
        "thumb": "https://i.ytimg.com/vi/-dCmRP2KBBo/mqdefault.jpg",
        "date": "2026-06-15",
        "url": "https://www.youtube.com/watch?v=-dCmRP2KBBo"
      },
      {
        "vid": "T-iYfkrB6fw",
        "title": "Cucurella against Real Madrid!",
        "thumb": "https://i.ytimg.com/vi/T-iYfkrB6fw/mqdefault.jpg",
        "date": "2026-06-15",
        "url": "https://www.youtube.com/watch?v=T-iYfkrB6fw"
      },
      {
        "vid": "t6ch9m58Fwg",
        "title": "How did he score that? 🤯",
        "thumb": "https://i.ytimg.com/vi/t6ch9m58Fwg/mqdefault.jpg",
        "date": "2026-06-15",
        "url": "https://www.youtube.com/watch?v=t6ch9m58Fwg"
      }
    ]
  }
}